pytrends_httpx/__init__.py
pytrends_httpx/dailydata.py
pytrends_httpx/exceptions.py
pytrends_httpx/request.py
pytrends_httpx-1.0.0.dist-info/LICENSE
pytrends_httpx-1.0.0.dist-info/METADATA
pytrends_httpx-1.0.0.dist-info/WHEEL
pytrends_httpx-1.0.0.dist-info/top_level.txt
pytrends_httpx-1.0.0.dist-info/RECORD
