Metadata-Version: 2.1
Name: pytrends-httpx
Version: 1.0.0
Summary: Pseudo API for Google Trends - Async version with httpx
Home-page: https://github.com/hctpbl/pytrends-httpx
Author: Héctor Pablos
Author-email: hectorpablos@gmail.com
License: Apache 2.0
Keywords: google trends api search async asyncio httpx
Platform: UNKNOWN
Classifier: Development Status :: 4 - Beta
Classifier: Environment :: Web Environment
Classifier: Framework :: AsyncIO
Classifier: Framework :: Trio
Classifier: Intended Audience :: Developers
Classifier: License :: OSI Approved :: Apache Software License
Classifier: Operating System :: OS Independent
Classifier: Programming Language :: Python :: 3
Classifier: Programming Language :: Python :: 3 :: Only
Classifier: Programming Language :: Python :: 3.7
Classifier: Programming Language :: Python :: 3.8
Classifier: Programming Language :: Python :: 3.9
Classifier: Topic :: Internet :: WWW/HTTP
Requires-Python: >=3.7.1
Requires-Dist: httpx (==0.16.*)
Requires-Dist: pandas (>=0.25)
Requires-Dist: lxml
Requires-Dist: tenacity (>=6.3)
